lntlvs/__init__.py
lntlvs/cli.py
lntlvs/load_custom_records.py
lntlvs/tlv_keys.py
lntlvs/generated/__init__.py
lntlvs/generated/lightning_pb2.py
lntlvs/generated/lightning_pb2_grpc.py
lntlvs-0.0.1.dist-info/LICENSE
lntlvs-0.0.1.dist-info/METADATA
lntlvs-0.0.1.dist-info/WHEEL
lntlvs-0.0.1.dist-info/entry_points.txt
lntlvs-0.0.1.dist-info/top_level.txt
lntlvs-0.0.1.dist-info/RECORD
