Metadata-Version: 2.1
Name: lntlvs
Version: 0.0.1
Summary: Extract custom metadata records that may have been attached to lightning payments you received
Home-page: https://github.com/seetee-io/lntlvs
Author: @dnlggr
Author-email: hello@seetee.io
License: GPL-3.0-only
Platform: UNKNOWN
Requires-Python: >=3.7
License-File: LICENSE
Requires-Dist: click (<9,>=8.0.3)
Requires-Dist: grpcio (<2,>=1.42)
Requires-Dist: googleapis-common-protos (<2,>=1.53)
Provides-Extra: dev
Requires-Dist: grpcio-tools (<2,>=1.42) ; extra == 'dev'
